schemaobject/__init__.py
schemaobject/collections.py
schemaobject/column.py
schemaobject/connection.py
schemaobject/database.py
schemaobject/foreignkey.py
schemaobject/index.py
schemaobject/option.py
schemaobject/procedure.py
schemaobject/schema.py
schemaobject/table.py
schemaobject/trigger.py
schemaobject/view.py
SchemaObject-0.5.10.dist-info/LICENSE
SchemaObject-0.5.10.dist-info/METADATA
SchemaObject-0.5.10.dist-info/WHEEL
SchemaObject-0.5.10.dist-info/top_level.txt
SchemaObject-0.5.10.dist-info/RECORD
