Metadata-Version: 2.1
Name: SchemaObject
Version: 0.5.10
Summary: Iterate over a MySQL database schema as a Python object.
Home-page: http://matuson.com/code/schemaobject
Author: Mitch Matuson, Mustafa Ozgur
Author-email: code@matuson.com, root@mit.sh
License: UNKNOWN
Keywords: MySQL,database,schema
Platform: UNKNOWN
Classifier: Intended Audience :: Developers
Classifier: License :: OSI Approved :: Apache Software License
Classifier: Programming Language :: Python
Classifier: Topic :: Software Development :: Libraries :: Python Modules
Classifier: Topic :: Database
Classifier: Topic :: Database :: Front-Ends
Requires-Dist: PyMySQL (>=0.6.2)
